[
  {
    "timestamp": "2025-05-15T06:28:04.829988",
    "country": "ソロモン諸島",
    "query": "ソロモン諸島 パビリオン 大阪万博",
    "links": [
      {
        "title": "新たに9か国から大阪・関西万博への公式参加が表明されました ...",
        "link": "https://www.expo2025.or.jp/news/news-20220531-01/"
      },
      {
        "title": "EXPO2025 大阪・関西万博 - 国際機関 太平洋諸島センター",
        "link": "https://pic.or.jp/featured_word/10255/"
      },
      {
        "title": "パビリオンマップ 大阪・関西万博2025｜NHK",
        "link": "https://www3.nhk.or.jp/news/special/osaka_expo/pavilion/"
      },
      {
        "title": "２０２５年日本国際博覧会（大阪・関西万博） の進捗状況",
        "link": "https://www.cas.go.jp/jp/seisaku/expo_suisin_honbu/kankei_renraku/dai5/siryou1.pdf"
      },
      {
        "title": "大阪・関西万博3回目3 コモンズa館写真集2とカタールパビリオン前 ...",
        "link": "https://ameblo.jp/bomuu/entry-12895014892.html"
      },
      {
        "title": "大阪・関西万博に関する関係者会合 １．日 時：2024 年 9 月 10 日 ...",
        "link": "https://www.cas.go.jp/jp/seisaku/osaka_kansai_banpaku/pdf/r60910_siryou1.pdf"
      },
      {
        "title": "（資料1）大阪・関西万博 関西パビリオンの取組状況について",
        "link": "https://www.kouiki-kansai.jp/material/files/group/3/1-170shiryo1.pdf"
      },
      {
        "title": "Sou Fujimoto 藤本壮介 (@soufujimoto) / X",
        "link": "https://x.com/soufujimoto"
      },
      {
        "title": "1 今週の大阪・関西万博 週報（11/26～12/2） ～ 開催まで あと ...",
        "link": "https://www.shikoku.meti.go.jp/03_sesakudocs/0310_expo2025/weeklyreport/241126-1202.pdf"
      },
      {
        "title": "今後の予算執行及びスケジュール等について",
        "link": "https://www.meti.go.jp/shingikai/mono_info_service/expo_budget_monitoring/pdf/005_04_00.pdf"
      }
    ],
    "gemini_summary": "提供されたテキストからは、大阪万博への参加状況に関する完全なリストは得られません。断片的な情報しかありません。\n\n明確な情報は次の通りです。\n\n* **太平洋諸島センター（PIC）の報告:** ツバル、ナウル、フィジー、ミクロネシア連邦、マーシャル諸島など、少なくとも11か国の太平洋島嶼国が共同館に出展するとあります。フィジーはエキシビジョンブースとコマーシャルブースの両方に出展するようです。\n\n* **食い倒れダイエット日記ブログ:**  ソロモン諸島、グレナダ、コモロ、ルワンダ、キルギス、スリランカ、バルバドス、モーリシャス、ケニア、ガーナがコモンズA館に出展しているとあります。また、カタールがナショナルデーイベントを開催していたことが記載されています。\n\nそれ以外のテキストからは、各国パビリオンの参加状況に関する具体的な情報は抽出できませんでした。提供されたPDFファイルや、アクセスに失敗したX（旧Twitter）および政府関連ウェブサイトのデータが不足しているためです。\n\n\nこれらの情報から、大阪万博には多数の国が参加するものの、具体的な参加国リストやパビリオン数については、公式発表やより詳細な情報源を参照する必要があると結論づけられます。\n"
  },
  {
    "timestamp": "2025-05-15T06:28:17.559240",
    "country": "イタリア",
    "query": "イタリア パビリオン 大阪万博",
    "links": [
      {
        "title": "イタリアパビリオン also hosting the Holy See - 大阪・関西万博",
        "link": "https://www.expo2025.or.jp/official-participant/italy/"
      },
      {
        "title": "L'ITALIA A EXPO 2025 OSAKA | イタリア館",
        "link": "https://www.italyexpo2025osaka.it/ja/itariaguan"
      },
      {
        "title": "「本物を見ることの意義」関西万博・イタリアパビリオン展示物の ...",
        "link": "https://news.yahoo.co.jp/articles/1f095a575d9b62fd1c0049dfde65292399461d75"
      },
      {
        "title": "2025年大阪万博のイタリア館は",
        "link": "https://www.italyexpo2025osaka.it/ja"
      },
      {
        "title": "【大阪万博】大人気のイタリア館！別ルートでパビリオン予約 ...",
        "link": "https://ameblo.jp/photolife-memorial/entry-12895866665.html"
      },
      {
        "title": "Yasko Fujii | 「大阪関西万博2025」イタリア館 ...",
        "link": "https://www.instagram.com/p/DFHEPRihcB2/"
      },
      {
        "title": "【大阪・関西万博へ行こう】イタリア館の予約はアプリからでき ...",
        "link": "https://ameblo.jp/hirarajal/entry-12895059983.html"
      },
      {
        "title": "Italy Expo 2025 Osaka (@ItalyExpo2025) / X",
        "link": "https://x.com/italyexpo2025"
      },
      {
        "title": "イタリアとパソナグループが文化プログラムで連携 大阪・関西万博 ...",
        "link": "https://www.pasonagroup.co.jp/news/index112.html?itemid=5318&dispmid=798"
      },
      {
        "title": "イタリアの人類学的仮面 | 大阪・関西万博テーマウィーク",
        "link": "https://theme-weeks.expo2025.or.jp/program/detail/6814be357866f.html"
      }
    ],
    "gemini_summary": "提供されたテキストから、大阪万博におけるイタリアパビリオンの参加状況を要約すると以下のようになります。\n\nイタリアは大阪万博にパビリオンを出展しており、バチカン市国も共同で運営に参加しています。  パビリオンは、古代ローマ時代の「ファルネーゼのアトラス」、カラヴァッジョの「キリストの埋葬」、レオナルド・ダ・ヴィンチの直筆スケッチなど、国宝級の貴重な芸術品を展示することで大きな注目を集めています。これらの展示物はレプリカではなく、本物である点が強調されています。  パビリオンへの入場には、公式アプリからの予約が必要となる場合があり、人気のため予約が困難な状況にあるようです。  イタリア館の公式アプリ「Italy Expo 2025」から予約枠を確認できるものの、特に人気時間帯はすぐに埋まってしまうとのことです。  コロッセオ風の外観も特徴の一つとなっています。\n\nその他の国のパビリオンに関する情報は、提供されたテキストからは読み取れませんでした。  イタリアパビリオンの情報が圧倒的に多く、他の国の参加状況については言及がありません。\n"
  },
  {
    "timestamp": "2025-05-15T06:28:30.544690",
    "country": "インドネシア",
    "query": "インドネシア パビリオン 大阪万博",
    "links": [
      {
        "title": "インドネシアパビリオン | EXPO 2025 大阪・関西万博公式Webサイト",
        "link": "https://www.expo2025.or.jp/official-participant/indonesia/"
      },
      {
        "title": "Expo2025 大阪・関西万博 | The Indonesia Pavilion / インドネシア ...",
        "link": "https://www.instagram.com/p/C6s6GRiu_ZW/"
      },
      {
        "title": "大阪・関西万博リターンズ その①海外パビリオン・マレーシア ...",
        "link": "https://ameblo.jp/mamehana0705/entry-12897501153.html"
      },
      {
        "title": "2025年大阪・関西万博「インドネシアパビリオンの設計・建設 ...",
        "link": "https://www.fujiya-net.co.jp/news/20240501"
      },
      {
        "title": "『EXPO 2025 大阪・関西万博』笑顔あふれるインドネシア ...",
        "link": "https://note.com/yamada_tourist/n/n27bea8822b97"
      },
      {
        "title": "インドネシアパビリオン：2025大阪・関西万博パビリオン紹介 ...",
        "link": "https://www.nippon.com/ja/guide-to-japan/expo2025021/"
      },
      {
        "title": "インドネシアパビリオン｜最高の没入感！映像が凄い｜大阪・関西 ...",
        "link": "https://note.com/nobuo_itsuki/n/nc10e4284d765"
      },
      {
        "title": "大阪・関西万博 インドネシアパビリオン ビジネスイベントご案内 ...",
        "link": "https://bkpm-jpn.com/osakaexpo2025/"
      },
      {
        "title": "万博のインドネシア館マスコットにバティック文様キャラ ...",
        "link": "https://plus62.co.id/archives/33221"
      },
      {
        "title": "大場亜沙美 | 大阪関西万博MC インドネシアパビリオン on X ...",
        "link": "https://x.com/Asamicantik/status/1914324854511452450"
      }
    ],
    "gemini_summary": "提供されたテキストから、2025年大阪・関西万博におけるインドネシアパビリオンの参加状況を要約すると以下のようになります。\n\nインドネシアパビリオンは、「調和の繁栄」をテーマに、「船」をモチーフとしたデザインで建設されました。これは、世界最大の群島国であるインドネシアの島々を行き交いながら発展してきた歴史と、新首都ヌサンタラの建設など未来への取り組みを象徴しています。\n\nパビリオン内では、熱帯雨林の再現、多様な工芸や食文化の紹介、再生可能エネルギーへの取り組みなどの展示が行われています。  複数の没入型の大型映像展示が特徴で、高い評価を得ているようです。  さらに、ビジネスフォーラムやワークショップなども開催されました。\n\nマスコットキャラクターとして、バティック文様を基にした「トゥムトゥム」が採用されています。これは、インドネシアの伝統文化と日本のアニメ文化を融合したデザインとなっています。\n\n全体として、インドネシアパビリオンは、自然、文化、未来を融合させ、インドネシアの魅力を多角的に紹介する、来場者にとって印象的な体験を提供する場として設計・運営されていることがわかります。  他の国のパビリオンの状況については、断片的な情報しか得られませんでした。\n"
  }
]