{
  "イタリアパビリオン also hosting the Holy See - 大阪・関西万博": {
    "url": "https://www.expo2025.or.jp/official-participant/italy/",
    "text": "イタリアパビリオン also hosting the Holy See | EXPO 2025　大阪・関西万博公式Webサイト\n公式ブログ\n公式SNS\nGoods & Shops\nグルメ\n会場マップ\nユニバーサル情報\nアクセス\nマイチケットログイン\nお問い合わせ\n万博とは\n開催概要\n>\n開催目的\n>\n基本計画\n>\nステートメント\n>\nデジタルウォレット\n>\nキャッシュレス\n>\nテーマウィーク\n>\n持続可能性\n>\nデータ利活用\n>\n公式キャラクター\n>\nマスターライセンスオフィス\n>\nオフィシャルオンラインストア\n>\nデザインシステム\n>\nロゴマーク\n>\nオフィシャルテーマソング\n>\nアンバサダー\n>\nシニアアドバイザー\n>\nスペシャルサポーター\n>\nプロデューサー\n>\n万博を楽しむ\n海外パビリオン\n>\n国内パビリオン\n>\nシグネチャーパビリオン\n>\n大屋根リング\n>\nイベント情報\n>\n関連イベント\n>\n未来社会ショーケース\n>\nスタンプラリー\n>\nミャクミャクの日記\n>\n公式ブログ\n>\n公式SNS\n>\n公式アプリ情報\n>\nグッズ＆ショップ\n>\nグルメ\n>\n万博に行く\nご来場の前にご確認ください\n>\n会場情報\n>\nアクセス\n>\n会場マップ\n>\n主な施設情報\n>\nユニバーサル情報\n>\nEXPO 2025 Visitors\n>\nパンフレット\n>\n旅行情報\n>\n公式観光ガイド（体験予約など）\n>\nチケットインフォメーション\n>\n紙チケット/引換券\n>\n新着情報\nお知らせ\n>\nプレスリリース\n>\n活動報告\n>\n協賛・参加\nベストプラクティス\n>\nCo-Design-Challenge\n>\nTEAM EXPO 2025\n>\n営業参加\n>\n一般参加催事\n>\nテーマウィーク協賛\n>\nテーマ事業協賛\n>\n会場整備参加・運営参加\n>\n未来社会ショーケース事業出展\n>\n広報・プロモーション参加\n>\n参加特典\n>\n中小企業・小規模企業者向け\n>\n修学旅行・校外学習\n>\nジュニアEXPO2025教育プログラム\n>\nEXPO PLL Talks\n>\nEXPO COMMONS\n>\n協会情報\n協会情報\n>\n役員一覧\n>\n組織図\n>\n定款・規程\n>\n業務・財務情報\n>\n寄付\n>\n会場整備・交通アクセス情報\n>\n契約情報\n協会の契約情報\n>\n公式参加者による\nパビリオン契約情報\n>\nlanguage\n日本語\nEnglish\n简体中文\n繁體中文\n한국어\nFrançais\nEspañol\nlanguage\n日本語\nEnglish\n简体中文\n繁體中文\n한국어\nFrançais\nEspañol\n公式ブログ\n公式SNS\nGoods & Shops\nグルメ\n会場マップ\nユニバーサル情報\nアクセス\nマイチケットログイン\nお問い合わせ\nABOUT\n万博とは\n開催概要\n開催目的\n基本計画\nステートメント\nデジタルウォレット\nキャッシュレス\nテーマウィーク\n持続可能性\nデータ利活用\n公式キャラクター\nマスターライセンスオフィス\nオフィシャルオンラインストア\nデザインシステム\nロゴマーク\nオフィシャルテーマソング\nアンバサダー\nシニアアドバイザー\nスペシャルサポーター\nプロデューサー\nENJOY\n万博を楽しむ\n海外パビリオン\n国内パビリオン\nシグネチャーパビリオン\n大屋根リング\nイベント情報\n関連イベント\n未来社会ショーケース\nスタンプラリー\nミャクミャクの日記\n公式ブログ\n公式SNS\n公式アプリ情報\nグッズ＆ショップ\nグルメ\nVISIT\n万博に行く\nご来場の前にご確認ください\n会場情報\nアクセス\n会場マップ\n主な施設情報\nユニバーサル情報\nEXPO 2025 Visitors\nパンフレット\n旅行情報\n公式観光ガイド（体験予約など）\nチケットインフォメーション\n紙チケット/引換券\nNEWS\n新着情報\nお知らせ\nプレスリリース\n活動報告\nSPONSORSHIP\n協賛・参加\nベストプラクティス\nCo-Design-Challenge\nTEAM EXPO 2025\n営業参加\n一般参加催事\nテーマウィーク協賛\nテーマ事業協賛\n会場整備参加・運営参加\n未来社会ショーケース事業出展\n広報・プロモーション参加\n参加特典\n中小企業・小規模企業者向け\n修学旅行・校外学習\nジュニアEXPO2025教育プログラム\nEXPO PLL Talks\nEXPO COMMONS\nASSOCIATION\n協会情報\n協会情報\n役員一覧\n組織図\n定款・規程\n業務・財務情報\n寄付\n会場整備・交通アクセス情報\nCONTRACT\n契約情報\n協会の契約情報\n公式参加者による\nパビリオン契約情報\n©Copyright Japan Association for the 2025 World Exposition, All rights reserved.\nHOME\n海外パビリオン\nイタリアパビリオン also hosting the Holy See\nイタリアパビリオン also hosting the Holy See\n芸術は生命を再生する\nイタリア共和国\nイタリア\n公式情報\n芸術は生命を再生する\nイタリア館は、MCAマリオ・クチネッラ・アーキテクツがデザイン設計を手がけ、「アートは人生を再生する」というテーマを掲げています。\nルネサンス期の理想都市に着想を得た館内には、イタリアの都市文化を象徴する劇場、ポルティコ（列柱廊）、広場、庭園が配置されています。\nここでいう「アート」とは、イタリアが誇る美、創造性、そして卓越した職人技を指す「テクネ」を意味します。\n毎日午後6時からは、円形劇場にて多彩なライブパフォーマンスが繰り広げられます。\nまた、グランド・リングから望むイタリア館は、ファルネーゼ・アトラスを中心に、ティントレットやカラヴァッジョの名作などが展示される、まさに驚異のギャラリーとなっています。\nインフォメーション\n2024.01.12\n2025年日本国際博覧会「イタリアパビリオン」起工式を実施\nABOUT\n万博とは\n開催概要\n開催目的\n基本計画\nステートメント\nデジタルウォレット\nキャッシュレス\nテーマウィーク\n持続可能性\nデータ利活用\n公式キャラクター\nマスターライセンスオフィス\nオフィシャルオンラインストア\nデザインシステム\nロゴマーク\nオフィシャルテーマソング\nアンバサダー\nシニアアドバイザー\nスペシャルサポーター\nプロデューサー\nENJOY\n万博を楽しむ\n海外パビリオン\n国内パビリオン\nシグネチャーパビリオン\n大屋根リング\nイベント情報\n関連イベント\n未来社会ショーケース\nスタンプラリー\nミャクミャクの日記\n公式ブログ\n公式SNS\n公式アプリ情報\nグッズ＆ショップ\nグルメ\nVISIT\n万博に行く\nご来場の前にご確認ください\n会場情報\nアクセス\n会場マップ\n主な施設情報\nユニバーサル情報\nEXPO 2025 Visitors\nパンフレット\n旅行情報\n公式観光ガイド（体験予約など）\nチケットインフォメーション\n紙チケット/引換券\nNEWS\n新着情報\nお知らせ\nプレスリリース\n活動報告\nSPONSORSHIP\n協賛・参加\nベストプラクティス\nCo-Design-Challenge\nTEAM EXPO 2025\n営業参加\n一般参加催事\nテーマウィーク協賛\nテーマ事業協賛\n会場整備参加・運営参加\n未来社会ショーケース事業出展\n広報・プロモーション参加\n参加特典\n中小企業・小規模企業者向け\n修学旅行・校外学習\nジュニアEXPO2025教育プログラム\nEXPO PLL Talks\nEXPO COMMONS\nASSOCIATION\n協会情報\n協会情報\n役員一覧\n組織図\n定款・規程\n業務・財務情報\n寄付\n会場整備・交通アクセス情報\nCONTRACT\n契約情報\n協会の契約情報\n公式参加者による\nパビリオン契約情報\nお問い合わせ\n個人情報保護方針\n©Copyright Japan Association for the 2025 World Exposition, All rights reserved."
  },
  "Italy Expo 2025 Osaka (@italyexpo2025osaka) • Instagram photos ...": {
    "url": "https://www.instagram.com/italyexpo2025osaka/?hl=ja",
    "text": "Italy Expo 2025 Osaka(@italyexpo2025osaka) • Instagram写真と動画"
  },
  "イタリア館 - L'ITALIA A EXPO 2025 OSAKA": {
    "url": "https://www.italyexpo2025osaka.it/ja/itariaguan",
    "text": "L'ITALIA A EXPO 2025 OSAKA | イタリア館\nメインコンテンツへスキップ\nフッターへスキップ\nITA\nENG\n日本語\nフォローはここから\n検索\nOpen main menu\n私たちの紹介\nExpand submenu\n2025年大阪万博イタリア館\nExpand submenu\nプレス\nExpand submenu\nPartner e Sponsor\nExpand submenu\n募集と入札\nExpand submenu\n書類\nExpand submenu\nPrivacy policy\n私たちの紹介\n2025年大阪万博イタリア館\nプレス\nPartner e Sponsor\n募集と入札\n書類\nPrivacy policy\nフォローはここから\nITA\nENG\n日本語\nOpen main menu\n私たちの紹介\nExpand submenu\n2025年大阪万博イタリア館\nExpand submenu\nプレス\nExpand submenu\nPartner e Sponsor\nExpand submenu\n募集と入札\nExpand submenu\n書類\nExpand submenu\nPrivacy policy\n私たちの紹介\n2025年大阪万博イタリア館\nプレス\nPartner e Sponsor\n募集と入札\n書類\nPrivacy policy\nフォローはここから\nITA\nENG\n日本語\n検索\nHome\n/ 2025年大阪万博イタリア館\n/ イタリア館\nイタリア館\n2025年大阪万博のイタリア館は、建築家マリオ・クチネッラ氏\n共有する\n操作\nお役立ちリンク\n2025年大阪万博公式ウェブサイト\n在大阪イタリア総領事館\n在東京駐日イタリア大使館\n透明性\nアクセシビリティに関する声明\n透明な行政\nフォローはここから\n2025年大阪万博 イタリア館公式 アプリをダウンロード\n2025年大阪万博へのイタリア参加の代表委員会\n連絡先\n法人登録住所：\nファルネジーナ広場 1 - 00135 ローマ\nPEC:\nexpoosaka.commissariato@cert.esteri.it\n電話 +39 06 36915300\n法的通知\nプライバシーポリシー\nクッキーポリシー\n著作権"
  },
  "【大阪・関西万博】イタリア館は私の中でNo.1パビリオン ...": {
    "url": "https://yukonosuke.com/entry/osaka_banpaku_italy",
    "text": "【大阪・関西万博】イタリア館は私の中でNo.1パビリオン！｜アトラス・カラヴァッジョ・ダヴィンチの作品を日本で見れる感動✨３時間の待ち時間を短縮する今後の予約戦略は！？ - ゆこの気ままな京都暮らし\nゆこの気ままな京都暮らし\n旅行とカフェ巡りが大好きです❤️☕️ 好きなものを気ままに投稿していきます。\n当ブログはアフィリエイト広告を利用しています\nトップ\n>\n大阪万博\n>\n【大阪・関西万博】イタリア館は私の中でNo.1パビリオン！｜アトラス・カラヴァッジョ・ダヴィンチの作品を日本で見れる感動✨３時間の待ち時間を短縮する今後の予約戦略は！？\n2025\n-\n09\n-\n14\n【大阪・関西万博】イタリア館は私の中でNo.1パビリオン！｜アトラス・カラヴァッジョ・ダヴィンチの作品を日本で見れる感動✨３時間の待ち時間を短縮する今後の予約戦略は！？\n大阪万博\nずっと行きたかったイタリア🇮🇹パビリオンですが\n人気すぎるのでずっと見送ってました。\nやーっと予約が取れたので行けました❣️\nその期待以上❗️\n写真撮る手が止まらなないくらい😍\n素晴らしいパビリオンでした💚🤍❤️\n万博6回目で人気パビリオンはほぼ制覇した私ですが、その中でもNo.1のパビリオンでした。本物の芸術品が日本で観れるなんで凄すぎる！\nぜひお勧めしたいパビリオンなので、この記事ではイタリア館に特化して\n①イタリア館を予約する5つの方法\n②イタリア館の現地レポート\n③本場のピザ&ジェラートの“食の魅力”\nを解説します。\n【イタリア館の予約方法】\nイタリア館専用公式アプリ\n初めての方におすすめ。2か月前抽選と7日前抽選\n空き枠先着予約はなかなかハード\n最後の予約チャンス！？ただ意外と穴場な当日予約\n実際に行ってみてわかった、イタリア館のアートの凄さ\nミケランジェロの彫刻『復活のキリスト✝️』\nペルジーノの「正義の旗」　万博イタリア館で8/31より展示開始\nイタリア館のレストラン「EATALY（イータリー）」\n本場のジェラート・ピザで感動した「食の魅力」\n万博イタリア館仕様のミャクミャクグッズが受注販売へ変更。緑ミャクミャクやスクーターミャクミャクなどレアなグッズの注文方法は？\n【イタリア館の予約方法】\n休日に行ってきたのですが、当日並ぶとなると\n３時間\nも待つそうです。確かに３時間並ぶ価値はあるのですが、他にも素晴らしいパビリオンはたくさんあるので、事前に予約することをおすすめします。\nイタリア館専用公式アプリ\nイタリア館の予約は万博公式とイタリア館専用のアプリがあって、今回はアプリの方から予約が取れました。\n【公式アプリのダウンロード】\nios:\nItaly Expo 2025 – 公式アプリ\nCommissariato generale di sezione per la partecipazione italiana a Expo 2025 Osaka\n旅行\n無料\napps.apple.com\nandroid:\nplay.google.com\nただ、認知が拡大したこともあり、ほぼ全ての日程が完売しておりキャンセル枠も空く気配がありません。これから予約される方は、イタリア館公式アプリではなく、通常の万博サイトから予約することをお勧めします。チャンスは以下の4回です。\n2か月前抽選（２ヶ月前までに申し込み必要）\n7日前抽選（７日前までに申し込み必要）\n空き枠先着予約（３日前から前日までに申し込み必要）\n当日登録（入場後１０分後に申し込み可能）\n初めての方におすすめ。2か月前抽選と7日前抽選\nこちらは運次第ですが、先着予約に比べると自分の好きなタイミングで予約できるため、特に初めて万博に行かれる方は抽選予約でイタリア館を選ぶと良いです。５つまで選ぶことができますが、おすすめは「\n遅い時間帯\n」です。予約の倍率が高いのは午前中や日中のため、倍率の低い１７時以降で５つ候補を出しておくと比較的抽選が取りやすいです。これはイタリア館だけではなく、全てのパビリオン予約において有効です。\n空き枠先着予約はなかなかハード\n４月の時点ではそこまで予約サイトにアクセスする人も多くなかったせいか、３日前の０時に先着予約のアクセスしても待ち人数は２０００人程度でした。\nそれが５月に入って認知も高まったせいかなんと\n２０倍の４万人待ち\n！時間にして\n１時間以上\n待つ必要があります。３日前の予約でイタリア館の予約をしたい方は、必ず１時間以上前から予約画面に入れるようにしておいた方が良いです。ただ、争奪戦なので人気パビリオンは予約できない可能性の方が高いです。\n空き枠先着予約だと、開始して１時間程で予約枠なくなっていました😱\n最後の予約チャンス！？ただ意外と穴場な当日予約\n空き枠先着予約でイタリア館の予約ができなかったとしてもまだ当日予約があります。\n下記は朝９時１５分頃のイタリアパビリオンの空き情報です。１５時まではほぼ埋まっていたのですが、\n１５時以降は意外と当日予約でもいける\nことがわかりました。ということは？？\n１５時以降の予約がおすすめです！\n多くの人は午前中やなるべく早い時間帯に予約をとりたいため、競走倍率も高くなります。空いていたとしても秒単位で予約がとれなくなります。本気でイタリア館の予約をしたい方は、最初から倍率が低い１５時以降の予約がおすすめです。\n予約チャンスはここまでですが、朝一でいけば予約せずにそのままイタリア館に直行すると\n10-30分\n程度で入れます。\n並んでいる時にスマホの当日予約で他のパビリオンを予約すればさらに効率的！\n【2025年5月25日追記】\n5/24のイタリア館はなんと最大\n６時間待ち\nだったそうです。全パビリオンの中で一番人気のパビリオンだと思います。\n【2025年5月26日追記】\n公式から予約が5/31までとなっているため、\n6月以降の予約に関してはできない可能性が高いです\n。\n私も6月の7日前抽選予約をしようとしたらイタリア館が見当たりませんでした。6月以降は当日朝から並ぶのが確実かもしれません。逆に予約枠がなくなるので、その分並んだ時の待ち時間が少なくなるかもしれませんね！\nイタリア館の予約に関しては最新の情報が分かり次第反映していきます。\n【2025年6月4日追記】\nなんとイタリア間予約が再開したようです！\nただ予約できないときもあるみたいなので最新情報を常にチェックしておく必要がありそうです。予約画面の最初の画面に「イタリア館」は表示されるので検索不要で確認できます。深夜２時とかに解放されているケースもあるため、３日前予約が取れなかった方は特にチェックしておきましょう。ラッキーなことが起こるかもしれません！\nyukonosuke.com\n【2025年8月27日追記】\n万博会期終盤に近づいたことで、朝の予約争奪戦が激化しています。\nイタリア館の当日予約も９時１５分くらいにはなくなっていました。\nイタリア館に行きたい方は「朝９時入場の西ゲート」をおすすめします。ゲートへの到着はなるべく７時台を目指すと良いと思います。当日予約が取れなかった場合でも朝であれば比較的並ばずに入ることができます。\n下記の記事では、８時５７分には西ゲート入場する方法を解説していますので興味ある方は読んでみてください。この時間だと当日予約はイタリア館含め余裕でとることができます。\nyukonosuke.com\n【2025年9月14日追記】\n閉幕まで残り１ヶ月となり、そもそも９時入場自体が難しくなってきました。９時入場はタイミングとコツさえ掴めば可能です。詳細はこちらの記事をどうぞ。\nyukonosuke.com\n他の予約可能なパビリオンについても予約難易度や参考待ち時間と共にまとめたので予約戦略の参考にしていただければ嬉しいです。\n【大阪万博のパビリオンの予約難易度をまとめた記事はこちら】\nyukonosuke.com\n実際に行ってみてわかった、イタリア館のアートの凄さ\nイタリア🇮🇹は旅行✈️で行ったコトあるけれど\n行き尽くせないから何度でも行きたい‼️\nイタリア料理は美味しいし😋\n美術館は素晴らしいし、建物🏛️や街並みは\n美しいし人々は陽気だし〜って好きな国です。\n（スリ被害にあいそうになって怖い思いもしたけれど😱）\n今回のイタリア館は現地に行かないと会えない\n貴重な作品がわざわざ日本🇯🇵に\nやって来てくれるというのが話題ですね！\nイタリアと言えばサッカーも‼️\n有名選手のサイン入り✍️⚽️🥅\nこの階段の右のお部屋に入ると、、、\nわぁ⭐️\nここは美術館なの？\n万博会場からイタリア🇮🇹へタイムトリップ\nしたみたい🥰\n古代ローマ時代の彫刻‼️\n『ファルネーゼのアトラス』\n他にも作品あるのに\nここだけ圧巻のオーラを放っています🌈\nこれがレプリカでなく本物というのが\nとんでもなくすごいコトですね！\nサイドから見てみる！\n肩に天球儀🌍を担いでいるのです。\n筋肉がすごい💪\n逆サイドからも🫣\n後ろからの景色🫣\nセキュリティの人が\n見張ってますよ〜😎\n時間⏳になると次のグループが\n入ってくるので移動になりますが\n名残惜しくて何度も振り返っちゃう😘\n次の作品はカラヴァッジョの名作🖼️\n『キリストの埋葬』\nこちらはバチカン美術館が所有している作品🖼️\n今にも動き出しそうなくらい\nリアルに描かれていてホントにすごい❗️\n先日、バチカン市国の新しい教皇が選ばれて\n世界中が注目していましたね！\n進んでいくと、もう一度\n「ファルネーゼのアトラス」のお尻だけ\n拝めます🙏\nイタリア🇮🇹の映像コーナーを巡って、、、\nイタリア🇮🇹と言えばフェラーリ！🏎️\n車関連の作品の展示もあり。\nこのエリアは次の目玉作品レオナルドダヴィンチの直筆スケッチを見る列でものすごく\n滞留しているので結構待ちました。\n薄暗い場所に展示されていて\nスタッフさんが順に誘導しています。\n細かい部分まで描き込まれていて\nじっくり見たいけどね。\nみんなが覗き込むように\n見たいから時間かかっちゃうのは\n仕方ない。\nミケランジェロの彫刻『復活のキリスト✝️』\nそうそう‼️\nまたイタリア館🇮🇹に新しい作品が\n追加されるそうです。\nミケランジェロの彫刻『復活のキリスト✝️』\n５月１８日から１０月１３日まで。\nyukonosuke.com\nペルジーノの「正義の旗」　万博イタリア館で8/31より展示開始\n8月31日にさらに作品が追加されました。\nルネサンス絵画の名作・ペルジーノの「正義の旗」　が大阪万博にやってきました！なんとイタリア国外で展示されるのは初だそうです。会期終了の10月31日まで展示されます。一度イタリア館にきた人も、初めて行かれる方も　きっと魅了されるはずです。\nイタリア館の本気が本当に凄いですね！\n今後はさらに行くのが大変になると思いますが、これから行かれる方は\nファルネーゼの「アトラス」\nカラヴァッジョの「キリストの埋葬」\nレオナルドダヴィンチの「直筆スケッチ」\nミケランジェロの「キリストの復活」\nペルジーノの「正義の旗」\nなどのイタリア館のフルコースを一回で見ることができるので是非一度は行ってみることをおすすめします。\n並べばはいれますが、何時間も並ぶのが嫌な人は朝イチの西ゲート９時が以下の理由でおすすめです。\nイタリア館の当日予約枠が解放されるのは朝のみ\n西ゲート朝イチであれば最悪予約取れなくても並べばすぐ入れる\n下記の記事は万博で最も大変だった「サウジアラビアレストランの行き方」についてまとめていますが、朝のイタリア館もこの方法で攻略できるはずなので興味ある方はチェックしてみてください。\nyukonosuke.com\nyukonosuke.com\nイタリア館のレストラン「EATALY（イータリー）」\n見終わったらエレベーター🛗に乗って\n３階まで移動になります。\n３階のレストラン前に抜けるので\n入りたかったけど１時間以上待つというので\n諦めた。\n先日は朝一で行ってみたらまだオープンしてなかったし🤣\nなんかいつもタイミングが"
  },
  "イタリア館 中身詳細＆感想 ぼっち大阪関西万博通算8回目 | 娘との ...": {
    "url": "https://ameblo.jp/wakochi0316/entry-12905719318.html",
    "text": "イタリア館☆中身詳細＆感想☆ぼっち大阪関西万博通算8回目 | 娘とのキッザニア甲子園体験日記☆\nイタリア館☆中身詳細＆感想☆ぼっち大阪関西万博通算8回目 | 娘とのキッザニア甲子園体験日記☆\nホーム\nピグ\nアメブロ\n芸能人ブログ\n人気ブログ\n新規登録\nログイン\n娘とのキッザニア甲子園体験日記☆\n（2025年4月〜10月は大阪・関西万博体験記と化しております　笑）\nキッザニア甲子園にハマってます☆\n中学1年生の長女とのキッザニア甲子園体験(基本母子二人で)を中心に育児ブログ書きたいと思ってます☆(4歳、年中さんの次女も最近はよく登場します)\nブログトップ\n記事一覧\n画像一覧\n動画一覧\nイタリア館☆中身詳細＆感想☆ぼっち大阪関西万博通算8回目\n『激闘4時間！！イタリア館予約無し待機列詳細！ぼっち大阪関西万博8回目』\n『ドイツ＆シンガポール☆ぼっち大阪関西万博①☆通算7回目』↑夢洲駅の巨大液晶にたまに出てくるミャクミャクがお土産屋さんの紹介してて「買って買って買って」て露…\nameblo.jp\n↑\nこちらのつづきです\nイタリア館\n↑\nこの待ち列の幕を抜けると。。\nミニシアターがあり、\n座って「イタリアとは？」な映像を5分ほど鑑賞したのち、メイン展示に通されます\n↑伊藤マンショの肖像画\n2026年冬季オリンピックはイタリアであるんですね\n本物の\n聖火\n初めて見ました\n↑\nこれがなんなのかよくわからなかったんですが、光ってる部分が動いてて不思議でした\n↑\nこちらがSNSで話題のよく載ってる彫刻ですよね\nこの部屋での1番メイン展示やと思います\n（この彫刻に1人専属で警備員さんがついてた。異彩を放ってましたね）\n古代ローマ時代の彫刻\n『ファルネーゼのアトラス』\nギリシャ神話の巨神アトラスを描写した大理石彫刻だそう\nナポリ国立考古学博物館にいつもはあるらしい\n↑\nどの角度から撮るのが正解かわからず、ひとまずぐるっと一周撮ってみました　笑\n集団で移動していくツアー形式ではなく、\n個人で展示はわりとゆっくり好きなように見れます\n↑\n頭上に飛行機も飛んでます\n次の部屋まで少し待ち列があり、順番に通されます。\n『キリストの埋葬』\n普段はヴァチカン美術館にあるらしい\n新婚旅行でイタリア一周して、\n（予定詰め詰めで超忙しい激安弾丸ツアーですが笑　あの頃ユーロ安やったから乗り継ぎや空港での待ち時間が長かったものの破格で行けたけど今やあんな値段ではとても無理やろな。。\n遠い目）\nヴァチカン美術館も外観までは行ったんですが待ち時間がかなりあり、中には入れなかったのでこんな所で見れるとは\nそしてまた少し次の部屋に行くのに待ち時間があり、次の部屋へ。。\n（この部屋が1番みどころがあった気がする）\nミケランジェロの彫刻『キリストの復活』は、首都ローマがある\nラツィオ州\nを紹介するイベントで来てるらしい\n前の部屋で「キリストの埋葬」を観て、次の部屋で「キリストの復活」を観て\n埋葬と復活が一度にすぐ見れる\nってすごいよね\n笑\n↑\nこの日は\nラツィオ州\nでしたが、\n週替わりくらいで州に合わせて展示が変わるらしい\nさすが国全体世界遺産だらけの国はすごいね\n↑\n素敵な2種類の真っ赤なドレスもありました\nレオナルド・ダ・ヴィンチのコーデックス原本\nここは「お写真撮りながら動いてくださ〜い」「立ち止まらないでくださ〜い」みたいな感じで他の作品と違い、ゆっくり見れなくて残念\nあと、タイヤとか衛星とか現代の展示も所々にあります\n↑\nなんかこの土偶みたいなのかわいい　笑\n↑\n展示は以上であとはこの階段を登ると、\nレストランなどもある\n屋上庭園\nになります\n↑\n階段から見ると展示はこんな感じ\n↑\n本来は2階部分（\n黄色◯\nの部分）が\nショップ（お土産屋さん）みたいなんやけど、\nまだオープンしてないらしい\n。。\nこのおおらかな感じがイタリアっぽいけど\n残念\n〜\n泣\nこんだけ並んだし、何かイタリア館っぽいグッズ買いたかったなぁ。。泣\n↑\nショップと表示にも書いてあるので聞いてる方が他にも沢山いた\n↑\n屋上庭園はこんな感じ\n↑\nなんか巨大葉牡丹みたいなのや巣箱が所々に。。\n↑\nそして階段をおり、出口です\n↑\n出口にもジェラート屋さんとかピザ屋さんとかあります\nこのイタリア館公式キャラのグッズ作ったら売れそうやのになぁ。。\nイタリア館　感想\nここはもはや\n美術館\n本物の美術品がおしげもなく並び、\n圧巻ですし見応えもあります\nが、\n4時間\n並んでまで見たいかと言われると。。人によるとしか。。\n美術館、美術品などに興味がある方にとってはもう涙もの\nで、何時間並んででもこの展示を見る価値はあると思いますが、\nとりあえず人気みたいやし1回見とこ！\nみたいな私みたいな方にはどうやろ。。\n見る価値はありますが4時間は。。\n2時間待ちくらいが精一杯かなぁ。。\n一見の価値はもちろんあります！\n観れるならせっかくやし観たほうがいいと思いますが、\n予約を意地でも取った方がいい\n！\n予約が取れた日に行く日程を考えるとかでないと正直4時間も並ぶことに費やすのは\nもったいない\n4時間もあれば他の海外パビリオンやと4つは見れると思うしご飯食べたりお土産買ったりもっと楽しい時間に使う方が有意義やし満足度も高いと思う\nイタリアほど有名でなくても\n心にささるパビリオンは沢山ある\nし最近は少し並ぶけど\nコモンズD\nみたいにすぐ入れる上に珍しい国々勢揃いみたいなパビリオンもあるし。。\n是非是非難しいとは思うんやけど、\n予約を取れるまでねばるとかにした方が熱中症や体調面を考えてもいいかなと思う\n夜まで行ける方は夜やったらもっと待ち時間も減るやろし短い待ち時間になった時に並ぶとか！\n一見の価値あり\nなのは間違いない\n（会期中にショップオープンしたら\n是非行きたい。。\n）\nイタリアおおらかやからこのままショップ閉まったまま終わるってことも充分ありそうやけど。。泣\nこの2階のショップがオープンしたら導線も人の流れももっとよくなるんちゃうかなぁと思ったり。。\n（わからんけど）\nこの日の流れ\n10時20分〜東ゲート到着\n10時40分〜東ゲートより入場\n11時〜イタリア館に並ぶ\n〜ひたすらに並ぶ〜\n15時〜イタリア館　入館\n15時45分〜イタリア館　退館\n16時〜　東ゲートより帰宅\nこの日は\nイタリア館のみ\nぼっち大阪関西万博体験記\nへつづく。。\n『いのちのあかし☆ぼっち大阪関西万博通算7回目』\n↑オーストラリア館前に、前はカンガルーの着ぐるみがいたけど、今回はコアラの着ぐるみがいた 『ドイツ＆シンガポール☆ぼっち大阪関西万博①☆通算7回目』↑夢洲駅の…\nameblo.jp\n↑\nつづきはこちら\nブログトップ\n記事一覧\n画像一覧\nCopyright © CyberAgent, Inc. All Rights Reserved.\nスパムを報告\nお問い合わせ\n利用規約\nアクセスデータの利用\n特定商取引法に基づく表記\nヘルプ"
  },
  "「大阪・関西万博」一番人気のイタリアパビリオンをガチ解説 ...": {
    "url": "https://lovewalker.jp/elem/000/004/268/4268276/",
    "text": "「大阪・関西万博」一番人気のイタリアパビリオンをガチ解説！ カラヴァッジョの名画、ダ・ヴィンチの至宝が生で見られる！ ミケランジェロ「復活のキリスト」もやってくるって!? - エリアLOVE WALKER\nTOP\nニュース\nイベント\nグルメ\nスポット\n生放送\n企画\nコラム\nデジタル冊子\nレポート\nデータ\nTOP\nニュース\nイベント\nグルメ\nスポット\n生放送\n企画\nコラム\nデジタル冊子\nレポート\nデータ\nTOP\n「大阪・関西万博」一番人気のイタリアパビリオンをガチ解説！ カラヴァッジョの名画、ダ・ヴィンチの至宝が生で見られる！ ミケランジェロ「復活のキリスト」もやってくるって!?\nXトレンド解析で見る「大阪・関西万博」最新口コミ\n第10回\nエリアLOVEWalker総編集長・玉置泰紀「大阪・関西万博2025をブラタマキ」　第2回\n「大阪・関西万博」一番人気のイタリアパビリオンをガチ解説！ カラヴァッジョの名画、ダ・ヴィンチの至宝が生で見られる！ ミケランジェロ「復活のキリスト」もやってくるって!?\n2025年05月12日 19時00分更新\n文● 玉置泰紀（一般社団法人メタ観光推進機構理事）\nツイートする\nファルネーゼ・アトラスの前で筆者\nSNSから人気に火がついたイタリアパビリオン\n2025年大阪・関西万博を筆者が歩く連載の第2回は、大人気の「イタリアパビリオン」に行ってみた。\nエリアLOVEWalker総合研究所による、2025年4月28日～5月5日集計のXトレンド解析では、1位の「英国パビリオン」、2位の「大屋根リング」に続いて、3位がイタリアパビリオンとなっている。\nただ、英国パビリオンはアフタヌーンのメニュー騒ぎなので、パビリオンとしてはイタリアパビリオンが一番人気といえよう（\n櫻井翔が大阪・関西万博の大屋根リングに登場！ 5,000円アフタヌーンティーの“紙コップ騒動”も話題に\n）。\n多くのファンが集まるイタリアパビリオン。屋上はイタリア式庭園になっていて、イータリーのレストランがある。Courtesy of Italy Pavilion at Expo 2025 Osaka\nイタリアパビリオンで大きな話題を集めているのは、一堂に会していることが奇跡ともいえる、紀元2世紀の彫刻「ファルネーゼ・アトラス」、カラヴァッジョの絵画「キリストの埋葬」、レオナルド・ダ・ヴィンチの素描、といった世界の至宝が展示されていることだ。\nティントレットによって描かれた「伊東マンショの肖像」が出迎える展示空間 Courtesy of Italy Pavilion at Expo 2025 Osaka\nまた、屋上のイタリア式庭園やトリノで開業し世界中で人気を博すレストラン「イータリー」での食事なども喜ばれている。\nさらに、5月18日からミケランジェロの彫刻「復活のキリスト」の展示が始まり、閉幕する10月13日までパビリオンで観られるのだ。イタリア大好きの筆者もさっそく、人気パビリオンを訪れた。\n展示室の全体\n今となっては予約を取るのも大変で、多くの人が並ぶパビリオンだが、最初から人気だったわけではない。\nきっかけになったのはSNS。開幕以来、訪れた一般のお客さんの口コミで、このパビリオンにとんでもないものが展示されていることが一気に広まったのだ。\n1970年の大阪万博はもちろん、2005年の愛・地球博の段階でも、2006年に始まったTwitter（現X）などSNSは本格始動していなかった。つまり、日本で初めてのSNSがある本格大型「国際博覧会」が大阪・関西万博なのだ。\nルネサンスの理想都市を現代的に再解釈したパビリオン\nイタリアパビリオンのテーマは「L’Arte Rigenera la Vita（芸術が生命を再生する）」。\nイタリアの伝統と最新技術を融合させ、ルネサンスの理想都市を現代的に再解釈したパビリオンは、建築家マリオ・クチネッラ、MCA（マリオ・クチネッラ・アーキテクツ）による設計で、木造3階建ての構造に「ピアッツァ（広場）」「テアトロ（劇場）」「ジャルディーノ（庭園）」が再現されている。\nさらには、イタリアはカトリック文化を背景に、生物の多様性や人間の個性を尊重する哲学、多様性（ダイバーシティ）、「全ての生物が生まれながらに性を持ち、多様性を互いに認め合うべき」という考え方をパビリオンで表現しているという。\n夜のライトアップされた外観。Courtesy of Italy Pavilion at Expo 2025 Osaka\n万博会場のセービングゾーン（南東エリア）にあり、西ゲートからのアクセスが便利。“国宝級”のアートとしては、古代ローマの「ファルネーゼ・アトラス」、カラヴァッジョの「キリストの埋葬」、レオナルド・ダ・ヴィンチの直筆スケッチがあり、5月18日からは、ミケランジェロの「復活のキリスト」も展示される。\n最新技術としては、心臓移植などの先進医療技術のほか、持続可能な木造建築や最先端のデジタル技術も展示する。\n5月18日から展示されるミケランジェロ・ブオナローティ（1475年〜1564年）の『復活のキリスト』は、1514年〜1516年頃の製作で、。高さはおよそ205cmの大理石像。キリストの復活の瞬間を象徴し、右手に十字架を持つ姿で描かれる。大理石のなめらかな質感や布のドレープ、身体のやわらかさが特徴。普段はイタリア・ラツィオ州バッサーノ・ロマーノのサン・ヴィンチェンツォ・マルティーレ教会に安置されている。\nミケランジェロの作品はルネサンスの芸術的革新を体現し、カラヴァッジョの『キリストの埋葬』やレオナルドの素描とともに、過去と現代の対話を表現している。ミケランジェロの彫刻は、解剖学的に正確な身体表現と大理石の繊細な質感が特徴だが、『復活のキリスト』は、キリストの静かな威厳と復活の瞬間をとらえ、ルネサンスの理想美を体現した傑作。生で見るのが楽しみでならない。\n最新アートから古代ローマの名作まで\n見どころ満載の展示を紹介！\nそれでは、イタリアパビリオンの展示を紹介していこう。\n■ヤゴ 『循環器系』\nヤゴは心臓の鼓動を、科学的知識と技術的スキルから始まり、芸術的で感覚的な体験に変わる芸術作品に変えていく。このインスタレーションは、生命の継続的で無限のリズムを象徴するために円形に配置された30個の白い液体セラミックのハートで構成されている。\n■オリアナ・ペルシコ 『pneumOS』\nこの作品は、データを音に変換する5つのサウンド メンブレンと、都市の呼吸をシミュレートする呼吸バッグで構成されている。\nCourtesy of Italy Pavilion at Expo 2025 Osaka\n■ティントレット 『伊東 祐益 マンショ』\n1585年にドメニコ・ティントレットによって描かれた「伊東マンショの肖像」は、ミラノ・トリヴルツィオ財団コレクションのもの。この肖像画は、日本からの大使の訪問に際してヴェネツィア元老院の委嘱により制作されたもので、ヨーロッパにおける日本初の外交使節団「天正遣欧使節」を率いた若き貴族、伊東マンショが描かれている。\n53×43cmのキャンバスに油彩で描かれたこの肖像画には、東洋的な顔立ちの青年が、16世紀後半のスペインの流行を取り入れた優雅な服装で描かれている。\nこの肖像画の展示は、マウロ・ベッローニとクロマズーのクリエイティブ・チームによって実現された没入型ビデオによってより豊かなものとなっており、イザベッラ・カスティリオーニ教授のチームとブラッコ財団のコーディネートによる修復の際に、作品に対して行われた診断調査を詳しく見ることができる。\n2025年大阪万博におけるカスティリオーニの存在は、革新と国際協力の文脈の中で、東洋と西洋の文化間対話における重要人物を再発見する機会となるだろう。\n■ファルネーゼ・アトラス\n紀元2世紀の大理石彫刻。日本初公開であり、ナポリ国立考古学博物館の至宝。長いマントで覆われ、両手で肩の天球儀を持ち、猫背で膝を曲げたアトラスの姿が彫られている。ファルネーゼ・アトラスは、高さおよそ2メートル、重さ2トンもあり、科学的知識と巧みな芸術的技巧の融合を象徴している。\nアトラスが支える球体は、6mmの浅浮き彫りで精巧に彫られている。これは宇宙を象徴するもので、星座、星座、四方位、天と地が当時の理論に従って描かれている。天空を支えようとする巨人の努力を表現するという明らかな芸術的価値に加え、この作品には、何世紀にもわたって天文科学に影響を与えたもう一つの価値もある。\nというのも、天球上の星座の表現は、古代においてもっとも正確なものの一つなのだ。アトランテ・ファルネーゼでは、技術的・科学的知識が、普遍的な物語、巨人の労働への共感、作品の芸術性と融合しているといえる。\n人間の感性、発展、革新の間のつながりを求めることが大阪万博2025におけるイタリアのメッセージ。まさに、ファルネーゼ・アトラスが今回の旅に同行することになった理由だといえよう。\n■レオナルド・ダ・ヴィンチ 『アトランティックコード』\nミラノのヴェネランダ・アンブロジアーナ図書館所蔵の「アトランティックコード」から、厳選された4点の素描を展示している。これらは日本で初めての一般公開になる。来場者はレオナルド・ダ・ヴィンチ（1452-1519）の多才な才能（科学、技術、芸術、建築）を、直筆で間近で体感できる。\nイタリアパビリオンのテーマ「Art Regenerates Life（芸術は命を再生する）」に沿い、レオナルドの作品はルネサンスの芸術と科学の融合を象徴している。「アトランティックコード」はレオナルドが残した1119枚のシートからなるコレクションで、科学（解剖学、物理学）、技術（機械、飛行装置）、芸術（スケッチ）、建築（都市計画）など幅広い分野のメモや素描を含む。1637年以来、ヴェネランダ・アンブロジアーナ図書館が所蔵している。\n今回の展示は、ミラノ市とイタリアパビリオンの協力により実現した。レオナルドがミラノで活躍した時代（1482年〜1499年、1506年〜1513年頃）の文化的影響を強調し、ミラノが創造性とイノベーションの中心地であることを示している。\nレオナルドの作品は過去へのオマージュではなく、芸術・工学・科学の融合によるイタリアの革新性、そしてイタリアのダイナミックなアイデンティティーを世界に伝えている。\n厳選された4点は、万博期間中にローテーションで展示する。通常はミラノの図書館で厳重に保管されており、万博での展示は極めて稀な機会になる。\n■イタリアちゃん\nイタリアパビリオンのマスコットキャラクター「イタリアちゃん」\n©TOKIDOKI, LLC. Designed by Simone Legno\nイタリアちゃんは、イタリアパビリオンのマスコットキャラクター。\nもともと、イタリア（さかのぼればローマ帝国から）には、「イタリア・トゥッリタ（Italia turrita、砲塔のあるイタリアを意味する）」というイタリアを擬人化した女性として描く風習がある。砲塔がある（イタリア語で“トゥッリタ”）城壁の冠を頭上に頂いた若い女性の姿で表現されている。\nイタリアちゃんのオリーブの枝はイタリアの平和への意志を象徴し、国内和合と国際的な兄弟愛を包含している。一方、紋章の右側を縁取るオークの枝は、イタリア国民の強さと威厳を象徴している。\n©TOKIDOKI, LLC. Designed by Simone Legno\nイタリアちゃんの生みの親であるSimone Legno（シモーネ・レーニョ）は、tokidoki共同創設者兼チーフ・クリエイティブ・オフィサー。ローマに生まれ、幼い頃に絵を描き始めた。tokidokiブランドは2005年に設立され、ポップカルチャーのライフスタイル・シンボルとして国際的に認知されている。\nTokidokiは日本語で「ときどき」を意味し、日本と世界の文化に対する彼の愛情を明確に表し"
  },
  "イタリアちゃん メタルキーホルダー2種 万博 イタリアパビリオン ...": {
    "url": "https://www.patfrancis.org/mvmdirx-302561zitems/etid.html",
    "text": "イタリアちゃん メタルキーホルダー2種 万博 イタリアパビリオン 大阪万博 イタリアちゃん メタルキーホルダー｜Yahoo!フリマ（旧\nWWW.PATFRANCIS.ORG\n...\nすべて\n生活雑貨／キッチン用品\n飲料／食品／ギフト／お酒\n衛生／医療／介護\nDIY用品／園芸／資材\nテープ／梱包資材／店舗用品\n物流・現場用品／台車\n作業服／ワークウェア／安全保護具\nトナー／インク／コピー用紙\nパソコン／周辺機器／メディア\n事務機器／家電／電池／照明\nオフィス家具／収納\n事務用品／文房具\nファイル\n工具／電動工具\n切削工具／研磨材\n計測機器\n研究開発・クリーンルーム用品\n機械部品／空圧機器／電気・電子部品\n検索\n詳細設定\n検索範囲\n商品名・カテゴリ名のみで探す\n除外ワード\nを除く\n価格を指定（税込）\n指定なし\n指定なし\n100円\n200円\n500円\n1,000円\n3,000円\n5,000円\n10,000円\n20,000円\n30,000円\n40,000円\n50,000円\n60,000円\n70,000円\n80,000円\n90,000円\n100,000円\n～\n指定なし\n指定なし\n100円\n200円\n500円\n1,000円\n3,000円\n5,000円\n10,000円\n20,000円\n30,000円\n40,000円\n50,000円\n60,000円\n70,000円\n80,000円\n90,000円\n100,000円\n商品\n直送品、お取り寄せ品を除く\n検索条件を指定してください\n件が該当\n検索\nもっと詳細に指定する\nその他便利な検索\nトナー・インク検索\nボールペン替芯かんたん検索\nはんこ補充インクかんたん検索\nSMC製品検索\nカタログから探す\nメーカー名から探す\n50音から探す\nブランドから探す\nグリーン商品を探す\n各種お手続き\nヘルプ\nよくわかるアスクルWebサイト\n定期配送サービス お申込み一覧\n自動配送サービス お申込み一覧\n返品のお申込み（ご利用履歴から）\n修理のお問い合わせ\n納品書の再発行（ご利用履歴から）\n請求書の再発行\nカタログのお申込み\n登録情報の確認・変更\nパスワードの再発行\nトナー・カートリッジ回収のお申込み\n化学物質（SDS・RoHS）調査依頼\nヘルプ\n履歴・再注文\nご注文履歴から再注文や配送状況の確認ができます。\nマイカタログ\nお気に入りの商品を登録して自分のカタログを作れます。\nクイックオーダー\nお申込番号の入力で商品をまとめてご注文いただけます。\n30～80％OFFなどのお得な商品が続々入荷！\nアスクル新登場の商品を\nご紹介！\nお届け先\n〒135-0061\n東京都江東区豊洲3\n変更\nスイートポイント\nあとで買う\nカテゴリー\n生活雑貨／キッチン用品\n飲料／食品／ギフト／お酒\n衛生／医療／介護\nDIY用品／園芸／資材\nテープ／梱包資材／店舗用品\n物流・現場用品／台車\n作業服／ワークウェア／安全保護具\nトナー／インク／コピー用紙\nパソコン／周辺機器／メディア\n事務機器／家電／電池／照明\nオフィス家具／収納\n事務用品／文房具\nファイル\n工具／電動工具\n切削工具／研磨材\n計測機器\n研究開発・クリーンルーム用品\n機械部品／空圧機器／電気・電子部品\n専門商材・便利なサービスを探す\nアウトレット\nカタログから探す\n専門商材サービス\nスタンプ作成・印刷サービス\nオフィスづくりサービス\nアスクル定期配送サービス\nサイズ・専用オーダーサービス\nアスクル伊勢丹ギフトショップ\nお仕事に便利なサポートサービス\n電報\n勤怠管理（TouchOnTime）\n安否確認（Safetylink24）\nトナー・インクカートリッジ無料回収\nサポート・サービス一覧を見る\nカゴ\n点\nJavaScriptの設定が無効のため、アスクルWebサイトが正しく動作しません。\n設定を有効にする方法は\nこちら\nをご覧ください。\nお届け先の変更\n検索結果や商品詳細ページに表示されている「お届け日」「在庫」はお届け先によって変わります。\n現在のお届け先は\n東京都江東区豊洲3（〒135-0061）\nに設定されています。\nご希望のお届け先の「お届け日」「在庫」を確認する場合は、以下から変更してください。\n■\nアドレス帳から選択する（会員の方）\nログイン\n■\n郵便番号を入力してお届け先を設定（会員登録前の方）\n〒\n-\n入力した郵便番号で住所を検索する\n※郵便番号でのお届け先設定は、注文時のお届け先には反映されませんのでご注意ください。\n※在庫は最寄の倉庫の在庫を表示しています。\n※入荷待ちの場合も、別の倉庫からお届けできる場合がございます。\n変更しない\nこの内容で確認する\nホーム\nキャラクターグッズ\nキーホルダー・アクリルキーホルダー\nイタリアちゃん メタルキーホルダー2種 万博 イタリアパビリオン 大阪万博 イタリアちゃん メタルキーホルダー｜Yahoo!フリマ（旧\nメーカー\nパジコ\nパジコのアートパネル／インテリアアートを全て見る\nブランド\nパジコ（PADICO）\n商品情報を印刷する\nイタリアちゃん メタルキーホルダー2種 万博 イタリアパビリオン 大阪万博 イタリアちゃん メタルキーホルダー｜Yahoo!フリマ（旧\nレビューを書く\n1\nキャラクターグッズ/キーホルダー・アクリルキーホルダー 1位\n￥6300\n（税込）\n／￥5355（税抜き）\n販売単位：1本\nお申込番号：AYNTY5674306794\n／メーカー：イタリアちゃん メタルキーホルダー2種\n／型番：306794302561\n／JANコード：4233304002\n／アズワン／ナビス品番：\nお申込番号\nAYNTY5674306794\nメーカー\nイタリアちゃん メタルキーホルダー2種\n型番\n306794302561\nJANコード\n4233304002\n販売単位\n1本\n価格\n￥8,252（税込）\n／￥5355（税抜き）\n※こちらの商品は沖縄県・離島・その他一部地域・山間部で配送追加料金が発生します。地域等によっては、お届けできない場合もございますのでご了承ください。ご注文後、お届け不可の場合は、アスクルよりご連絡させて頂きます。\n直送品のため、以下の点にご注意ください。\nこちらの商品は沖縄県・離島・その他一部地域・山間部で配送追加料金が発生します。地域等によっては、お届けできない場合もございますのでご了承ください。ご注文後、お届け不可の場合は、アスクルよりご連絡させて頂きます。\nこの商品には、アスクル発行の納品書が同梱されていない場合があります。アスクル発行の納品書をご希望のお客様は、商品到着後、本サイト上のご利用履歴よりＰＤＦファイルにて印刷することが可能です。\nアスクルのダンボールもしくは袋でのお届けではありません。\nお客様のご都合によるご注文後の変更・キャンセル・返品・交換はお受けできません。\n商品のご注文後に商品がお届けできないことが判明した際には、ご注文をキャンセルさせていただくことがあります。\nご注文後に一時品切れが判明した場合は、入荷次第のお届けとなります。\n人気商品\nこの画像は代表画像です。詳細は仕様をご確認ください。\nすべて表示\nすべて表示\nすべて表示\n前のスライドへ\n次のスライドへ\n画像が似た商品\n前へ\n次へ\nイタリアちゃん メタルキーホルダー2種 万博 イタリアパビリオン 大阪万博 イタリアちゃん メタルキーホルダー｜Yahoo!フリマ（旧\nこの画像は代表画像です。詳細は仕様をご確認ください。\n※\n360°ビューの使い方\n在庫：\nわずか\n最寄り倉庫の在庫を表示しています。  「入荷待ち」でも別の倉庫からお届けできる場合もございます。\nお届け日：2025.09.04 10:34（月）まで\nお届け日は目安になります。詳細なお届け日に関しては、レジ画面にてご確認ください。\nお届け日表示について\nお届け先：\n東京都江東区豊洲3\n直送品\nLAB & Healthcare SHOP\nこの出荷元の商品は配送料が当社負担です。\n￥6300\n（税込）\n／ ￥5355 （税抜き）\n数量\n1\n2\n3\n4\n5\n6\n7\n8\n9\n10+\n数量\nカゴに入れる\nマイカタログ登録\nマイカタログ登録済み\n商品を比較\n比較したい商品を表に並べて、価格やスペック等を簡単に比べることができます。\n商品詳細\n商品情報の誤りを報告\n商品情報を印刷する\nご注意\n特別にお届けに日数がかかるなど、お買い上げにあたってご注意いただきたいことがある商品です。\r\n商品詳細画面に情報が記載してありますのでご購入前に商品詳細画面をぜひご確認ください。\n返品不可\nお客様のご都合による返品はお受けできません。\n直送品\n出荷元より直接お届けする商品です。一般商品とは別便でお届けとなります。レジ画面に表示されるのはお届け日の目安です。こちらの商品はお客様都合による返品をお受けできません。\nアスクル商品環境スコアとは\n商品の特徴\n大阪万博 イタリアちゃん メタルキーホルダー｜Yahoo!フリマ（旧。値下げ不可 イタリア 関西大阪万博 イタリア館 キーホルダー。イタリアちゃんキーホルダー⭐︎大阪万博イタリア館限定 - メルカリ。万博EXPO2025 イタリア館限定 イタリアちゃんメタルキーホルダー。大阪関西万博大阪万博イタリア館イタリアパビリオン入館者限定イタリアちゃんメタルキーホルダー２種\nメーカー名\nfd12dea96\nブランド名\nイタリアちゃん メタルキーホルダー2種\n備考\n【返品について】お客様のご都合による返品はお受けできません。\n商品詳細情報\nメーカーサイトはこちら\n家具・インテリアが探しやすい！アスクルの総合家具TOPページはこちら。\nレイアウト・各種工事・納期のご相談まで！アスクルオフィスづくりサービスはこちら。\n※\n免責事項\n本サービスでは、サイト上に最新の商品情報を表示するよう努めておりますが、メーカーの都合等により、商品規格・仕様（容量、パッケージ、原材料、原産国など）が変更される場合がございます。このため、実際にお届けする商品とサイト上の商品情報の表記が異なる場合がございますので、ご使用前には必ずお届けした商品の商品ラベルや注意書きをご確認ください。さらに詳細な商品情報が必要な場合は、製造元にお問い合わせください。また、販売単位における「セット」表記は、箱でのお届けをお約束するものではありません。あらかじめご了承ください。\nキーホルダー・アクリルキーホルダーの売れ筋ランキング\nランキングをみる\nキャラクターグッズ\n＞\nキーホルダー・アクリルキーホルダー\n＞\nイタリアちゃん メタルキーホルダー2種 万博 イタリアパビリオン 大阪万博 イタリアちゃん メタルキーホルダー｜Yahoo!フリマ（旧\n1\n人気商品\nツイステ バレンタイン 2025 リリア 4YOU チャーム&メッセージカード\n￥5,949～\n（税込）\n2\n人気商品\nリラックマ　ぶらさげぬいぐるみ　歴史　縄文　コリラックマ　キイロイトリ\n￥5,440～\n（税込）\n3\n人気商品\nホロライブ ジョイポリス　コラボ　常闇トワ 大当り　アクキー　当たり　ステッカー\n￥5,666～\n（税込）\n4\n人気商品\n【新品】サンリオキャラクターズ チョコボックス ボックスフィギュアコレクション\n￥5,760～\n（税込）\n5\n人気商品\n登坂広臣\n￥17,999～\n（税込）\n前のスライドへ\n次のスライドへ\nお客様レビュー\n投稿されたレビューはありません。お客様のレビューコメントをお待ちしております。\nレビューを書く\nこの商品に関連する特集\nS.H.MonsterArts ゴジラ (2016) シン・ゴジラ 覚醒ver\n真作/鹿子木孟郎/不倒/大黒図/大黒天図/福神図/掛軸☆宝船☆AH-704\nエアロアールシーTOMYTEC NISSAN SKYLINE GT-R(R34)\nstraykids hop 合 Walmart バンチャン リノ ヒョンラ\nサンドウィッチマンライブツアー2024 キン肉マンTシャツ　X"
  },
  "大阪・関西万博イタリアパビリオン公認イベント!! ～イタリアの旗手 ...": {
    "url": "https://prtimes.jp/main/html/rd/p/000000010.000099144.html",
    "text": "大阪・関西万博イタリアパビリオン公認イベント!! ～イタリアの旗手団による来日記念特別パフォーマンスを開催～ | 一般社団法人　国際カフェテイスティング協会ー日本のプレスリリース\nプレスリリース・ニュースリリース配信サービスのPR TIMES\nプレスリリースを受信\n企業登録申請\nTop\nテクノロジー\nモバイル\nアプリ\nエンタメ\nビューティー\nファッション\nライフスタイル\nビジネス\nグルメ\nスポーツ\n…\nPR TIMESのご利用について\n資料をダウンロード\n一般社団法人　国際カフェテイスティング協会ー日本\n会社概要\nフォロー\n大阪・関西万博イタリアパビリオン公認イベント!! ～イタリアの旗手団による来日記念特別パフォーマンスを開催～\nイタリア・カーヴァ市の旗手団「SBANDIERATORI CITTÀ DE LA CAVA - Li Quattro Distretti」 来日記念特別パフォーマンスを開催します。\n一般社団法人　国際カフェテイスティング協会ー日本\n2025年9月9日 13時00分\n2025年 9月11日（木）15:30～　 大阪ステーションシティ 5F 時空の広場\n大阪・関西万博イタリアパビリオンのブロンズスポンサーである一般社団法人 国際カフェテイスティング協会ー日本支部（東京都港区、以下「IIACJ」）は、イタリアパビリオンと共催し、1969年に設立されイタリアでも有名なイタリア・カーヴァ市の旗手団『SBANDIERATORI CITTÀ DE LA CAVA - Li Quattro Distretti』によるパフォーマンスイベントを大阪ステーションシティ5F 時空の広場にて実施いたします。\n2025年大阪・関西万博において、長時間待ち必至のイタリア館。その人気コンテンツが大屋根リングの外、大阪駅直結の万博サテライト会場「EXPO OSAKA STATION」で楽しめるイベントです。イタリア・ルネッサンスの伝統を現代に受け継ぎ、創造性や調和の理念を礎に、新たな価値を生み出し続ける伝統と芸術の迫力と華やかなパフォーマンスをご堪能ください。\n※カーヴァ・デ・ティッレーニ（Cava de’ Tirreni） は、イタリア南部カンパニア州サレルノ県にある都市です。\n＜イベント概要＞\n【日　程】 2025年9月11日（木）　15:30～16：15頃\n※当日スケジュールが変更される場合がございます。予めご了承ください。\n【場　所】 大阪ステーションシティ 5F 時空の広場\n（大阪ステーションシティ バール・デルソーレ隣のステージ）\n【費　用】 参加無料\n【参加・出演】挨拶：イタリア政府文化部門代表　ロッセッラ・メネガッツォ(Rossella Menegazzo)\n演奏：SBANDIERATORI CITTÀ DE LA CAVA - Li Quattro Distretti\n（イタリア・カーヴァ市の旗手団）\nSBANDIERATORI CITTÀ DE LA CAVA - Li Quattro Distretti\n■SBANDIERATORI CITTÀ DE LA CAVA - Li Quattro Distretti\n（イタリア・カーヴァ市の旗手団）\n1969年にルカ・バルバによって設立された、カーヴァ・デ・ティッレーニで最初にして最も歴史ある旗振りグループです。イタリア・ルネッサンスの伝統を現代に受け継ぐ存在として誕生しました。四つの地区それぞれが持つ独自の歴史と文化を融合させ、当時の芸術・建築・思想の精神を現代に蘇らせています。\n旗を操る古代からの芸術を受け継ぎながらも、演劇や文化活動にも力を注ぎ、カーヴァの街を代表する存在となっています。これまでにイタリア国内のみならず、15か国以上で公演を行い、ドバイ万博2020など国際舞台でもイタリアの伝統と誇りを世界に発信を続け、国内外で高い評価を得てきました。その活動は、歴史的再現劇「La Pergamena Bianca」や「国際衣装展」の開催など、多岐にわたります。\n公式サイト：\nhttps://www.sbandieratoricittadelacava.com/\n【観覧時の注意事項】\n●通路に立止まっての観覧は禁止させていただきます。\n●混雑の場合は、安全確保のためパフォーマンスを中止する場合がございます。(再開は致しません)\n●関係者の指示に従っていただけない場合は、観覧をお断りさせていただきます。\nこのプレスリリースには、\nメディア関係者向けの情報があります\nメディアユーザーログイン\n既に登録済みの方はこちら\nメディアユーザー新規登録\n無料\nメディアユーザー登録を行うと、企業担当者の連絡先や、\nイベント・記者会見の情報など様々な特記情報を閲覧できます。\n※内容はプレスリリースにより異なります。\nすべての画像\n種類\nイベント\nビジネスカテゴリ\n芸能\n交通・運送・引越し\nキーワード\n大阪・関西万博\nイタリア\nイタリア館\n万博\n大阪駅\nデルソーレ\nデルソーレ大阪\n時空の広場\n位置情報\n東京都\n港区\n（\n本社・支社\n）\n大阪府\n大阪市\n（\n公共施設・公共交通機関\n）\n関連リンク\nhttps://www.sbandieratoricittadelacava.com\nトップ\nプレスリリース\n一般社団法人　国際カフェテイスティング協会ー日本\n大阪・関西万博イタリアパビリオン公認イベント!! ～イタリアの旗手団による来日記念特別パフォーマンスを開催～\n会社概要\n一般社団法人　国際カフェテイスティング協会ー日本\n2\nフォロワー\nフォロー\nRSS\nURL\nhttp://coffeetasters.jp\n業種\n財団法人・社団法人・宗教法人\n本社所在地\n東京都港区麻布十番1-5-29-205\n電話番号\n03-5411-6619\n代表者名\n桃井　祐美子\n上場\n未上場\n資本金\n-\n設立\n2007年07月\nトレンド情報をイチ早くお届け\nPR TIMESを友達に追加\nPR TIMESのご利用について\n資料をダウンロード\n会社概要\nプライバシーポリシー\n利用規約\n報道関係者からのお問い合わせ\n企業様からのお問い合わせ\n一般の皆様からのお問い合わせ\nCopyright © PR TIMES Corporation All Rights Reserved.\nニュースリリース配信サービス\nPR TIMESとは\n料金・プラン\nプレスリリースを受信したい方へ\nプレスリリースを配信したい方へ\nレコメンドサービス\nPR TIMES STORY\n動画制作・動画PRならPR TIMES TV\n記者発表・イベント配信ならPR TIMES LIVE\nPR TIMES MAGAZINE\n広報PRの効果測定はWebクリッピング\nPR Editor\nタスク・プロジェクト管理ならJooto\n無料フォーム・FAQならTayori\nPR事例ならPR EDGE\n\"おしゃれでかわいくて、しあわせ\"な情報ならisuta\n今週の運勢ならisutaの12星座占い\nPR TIMES公式SNS\n公式Facebookページ\nFacebookカテゴリ\n公式Xページ\nXカテゴリ\n会社概要\nプライバシーポリシー\nコンテンツ基準\n利用規約\n報道関係者様からのお問い合わせ\n企業様からのお問い合わせ\n一般の皆様からのお問い合わせ\nCopyright © PR TIMES Corporation All Rights Reserved."
  },
  "［大阪・関西万博］海外パビリオン紹介_イタリア・バチカン ...": {
    "url": "https://mag.tecture.jp/culture/20250604-128331/",
    "text": "［大阪・関西万博］海外パビリオン紹介_イタリア・バチカン - TECTURE MAG（テクチャーマガジン） | 空間デザイン・建築メディア\nCATEGORY\nFEATURE\nCULTURE\nPROJECT\nBUSINESS\nPRODUCT\nCOMPETITION & EVENT\nJOB\nCONTENTS\nABOUT\nCONTACT\nOTHER SERVICE\nFOLLOW US\nYouTube\nInstagram\nTwitter\nFacebook\nPinterest\nPOPULAR TAGS\n東京\nリノベーション\nRenovation\nTokyo\n海外建築\nWood\n木造\nYouTube\n動画\n海外\n展覧会\nArt\n戸建住宅\nDesign\nサステナブル\n自然\nResidential\n開業\nHotel\nRC造\n中国\nJob\n採用\nRecruit\nホテル\n家具\nCafe\nカフェ\nプロジェクト\n大阪\nVIEW ALL TAGS\n広告掲載について\n事例掲載について\n求人掲載について\n取材依頼について\n©tecture.inc. All Right Reserved.\nPOPULAR TAGS\n東京\nリノベーション\nRenovation\nTokyo\n海外建築\nWood\n木造\nYouTube\n動画\n海外\n展覧会\nArt\n戸建住宅\nDesign\nサステナブル\n自然\nResidential\n開業\nHotel\nRC造\n中国\nJob\n採用\nRecruit\nホテル\n家具\nCafe\nカフェ\nプロジェクト\n大阪\nVIEW ALL TAGS\nお問い合わせ\nFEATURE\nCULTURE\nPROJECT\nBUSINESS\nPRODUCT\nCOMPETITION & EVENT\nJOB\nALL\nARCHITECTURE\nART\nBOOK\nFASHION\nFOOD\nMOVIE\nMUSIC\nTECHNOLOGY\nOTHERS\nCULTURE\nマリオ・クチネッラ・アーキテクツが設計した〈イタリアパビリオン also hosting the Holy See〉\n［大阪・関西万博］海外パビリオン紹介\nCULTURE\n2025.06.04\nパビリオンDATA\n設計\nマリオ・クチネッラ・アーキテクツ（Studio MCA-Mario Cucinella Architects）\nAoR（アーキテクト・オブ・レコード）\n松田仁樹建築設計事務所\nエリア\nセービングゾーン\nテーマ\n芸術は生命を再生する\nイタリアパビリオン also hosting the Holy Seeの見どころポイント！\n劇場空間を取り囲むように配置されたポルティコ\nルネサンス庭園の伝統を現代的に再解釈した屋上のイタリア式庭園\nイタリアパビリオン内にバチカンパビリオンを併設。テーマは「美は希望をもたらす」\n革新的なイタリアの技術と伝統の交差点を強調したパビリオン\nPhoto: Yumeng Zhu\n建築と形式言語\n〈イタリアパビリオン〉は、イタリアのホスピタリティと景観の価値を現代的な視点で再解釈した、開放的で浸透性があり、温かみのある建築です。そのデザインは、透明性、自然光、そして有機的な素材が空間を定義し、訪れる人々の体験を形づくる、流動的でモジュール化された言語を生み出しています。\n建物本体は大きなエントランスホールを中心に構成され、内部を遮蔽しながら自然光を取り込む透明で通気性のあるファサードで縁取られています。外壁は、透過性のあるミネラルファイバー膜でできた半透明のテキスタイルファサードで、パッシブな温度と光の調節機能を強化し、建物の一時的、かつ可逆的な性質を強調しています。\nこの外壁は日射のコントロール、自然換気の促進、エネルギー消費の削減に貢献し、内部と外部の関係を明確にし、光、空気、温度を調整し、周辺環境との連続的な関係を築くうえで積極的な役割を果たします。梁と柱の格子は、日本の技術システムの知恵によってイタリアの格天井を再現し、1日を通して変化する影をつくり出します。建築のアーティキュレーションは柔軟性と可逆性の原則を反映し、外壁は大阪の気候や光の条件を緩和するように設計されています。\nPhoto: Yumeng Zhu\nPhoto: Yumeng Zhu\nパビリオンは2つのボリュームに分かれています。メインボリュームは展示体験を収容する大型格納庫と、見学可能な大きなテラスを備えた屋上で構成されています。\n屋上庭園は、イタリア庭園の伝統に着想を得た、複雑な生態系として現代的に再解釈された屋上庭園です。緑の有機的なデザインは展示風景に反映され、万博会場の円形リングと対話することで、パノラマビューと体験的な没入感の対比を生み出しています。素材から形状に至るまで、すべての建築要素は環境への影響を最小限に抑え、人、建築、自然の間の繊細なつながりを促進するように選択されています。\n建物は周囲の環境を支配することなく、大阪湾に調和的に溶け込み、イタリアのデザイン文化の真髄である持続可能性と美しさの関係を体現しています。\nPhoto: Yumeng Zhu\nリバーシブル建築\nパビリオンの設計は、建物のライフサイクル全体にわたる再生可能な持続可能性を根底とする体系的なアプローチを採用しています。構想段階から、設計では作業の一時性を制約ではなく、建築と組み立ての方法を再考する機会と捉えてきました。\n再生可能資源である集成材を使用し、乾式工法とモジュール工法を採用。これらの選択により、生産と組み立ての段階を簡素化し、廃棄物を削減し、材料の使用を最適化し、建設現場の各段階で確実に管理することが可能になります。設計プロセス全体は、分解を考慮した設計（DfD）と製造と組み立てを考慮した設計（DfMA）の原則に基づいており、部品点数の削減、サイクル終了時の分離の容易化、長期的な価値の維持を目的としています。ライフサイクル思考戦略に着想を得たこのアプローチは、効率性、耐久性、建築品質への要求を犠牲にすることなく、環境への影響を抑制し、建築、循環型経済、地域生産チェーンの統合を促進します。\nエネルギー効率と資源管理\n事前の詳細な気候分析により、自然換気システム、パッシブクーリング、ダイナミックシェーディングシステムをプロジェクトに組み込むことができ、全体的なエネルギー必要量を大幅に削減することができました。\nPhoto: Yumeng Zhu\nPhoto: Yumeng Zhu\nPhoto: Yumeng Zhu\nPhoto: Yumeng Zhu\n万博後の解体と再利用\n〈イタリアパビリオン〉は設計段階から、仮設ながらも永続的な建物として構想され、2025年万博の6カ月間をはるかに超えて存続する文化的、技術的、そして環境的遺産となることが期待されていました。プレハブの積層木材モジュールで完全に建設されたこの構造は、完全に解体できるように設計されています。これにより、新しい文脈で全体または一部の再利用が可能になり、イタリア国内外で文化センター、教育拠点、または展示スペースとして第二の人生を送ることができます。\n構造、材料、技術、家具に至るまで、すべての要素はトレーサビリティ、可逆性、柔軟性を考慮して設計されており、廃棄物を最小限に抑え、公共投資の長期的な価値を最大化することを目指しています。\nPhoto: Yumeng Zhu\n建築DATA\nクライアント：2025年大阪・関西万博イタリア参加代表委員会\n所在地：日本、大阪\n延床面積：3,000m²\n建築設計：Mario Cucinella Architects （マリオ・クチネッラ・アーキテクツ）\nアーキテクト・オブ・レコード：松田仁樹建築設計事務所、Arch5\n構造設計：Buromilan\n環境設計：Tekser Srl\nマルチメディアデザイン：Zeranta Edutainment Srl\n火災予防・安全管理：GAE Engineering Srl\n地質解析：Claudio Preci\nプロジェクトマネジメント：Beyond Limits\n施工（構造・建築・植栽）：西尾レントオール\n施工（内装）：乃村工藝社\nMCAチーム：Mario Cucinella、Giovanni Trogu（プロジェクト・ディレクター）、Michele Olivieri（デザイン・リーダー）、Alessio Naldoni（テクニカル・ユニット）、Fabrizio Bassetta（BIMマネージャー）、Luca Tiozzo（プロジェクト・リーダー）、Lapo Medici（設計）、Lorenzo Mancini（設計）、Beatrice Vara（設計）、Diego Baronchelli（ランドスケープデザイナー）、Tommaso Boschi（設計）、Fabiola Verde、Francesco Visco（設計）、Valentina Torrente（設計）、Angelo Ungarelli（設計）、Arianna Bartolotti（設計）、 Marcello Michelini（設計）、Mara Nunziante（設計）、 Giacomo Righi（設計）、 Augusta Zanzillo（設計）、Lori Zillante（R&Dユニットマネージャー）、Lapo Naldoni（R&D）\nトップ写真撮影：Yumeng Zhu\n※ テキスト、写真はマリオ・クチネッラ・アーキテクツ （MCA） 提供\n『TECTURE MAG』大阪・関西万博 ニュース＆特集一覧\nhttps://mag.tecture.jp/tag/expo2025/\n2025年「大阪・関西万博」TOPICS\nCOMPETITION & EVENT\n2025.04.11\n大阪・関西万博いよいよ開幕！\n4月13日から始まる万博の基本情報からパビリオンの紹介記事とマップを公開\nFEATURE\n2025.04.12\n事前に知りたい！大阪・関西万博の会場構成\nパビリオンの計画へとつながるテーマ、コンセプト、基本計画を解説\nCOMPETITION & EVENT\n2024.05.31\n大阪・関西万博 トイレなど20施設のイメージパースと設計コンセプト公開\nプロポーザルで選出された若手建築家20組による20のデザイン\nFEATURE\n2025.04.11\nシグネチャーパビリオンを一挙紹介！\n[大阪・関西万博]各分野のトップランナーが見据える未来を映す、個性豊かな8つのパビリオン\n【購読無料】空間デザインの今がわかるメールマガジン　TECTURE NEWS LETTER\n今すぐ登録！▶\nTAGS\n2025年大阪・関西万博\nexpo2025\nOsaka\nStudio MCA-Mario Cucinella Architects\nイタリア\nパビリオン\nマリオ・クチネッラ\n大阪\n松田仁樹建築設計事務所\n海外パビリオン\nSHARE\nALL\nARCHITECTURE\nART\nBOOK\nFASHION\nFOOD\nMOVIE\nMUSIC\nTECHNOLOGY\nOTHERS\nRECOMMENDED ARTICLE\nCULTURE\n2023.01.20\n板坂諭設計、パソナのパビリオンは「心臓（いのち）の螺旋 ～アンモナイトからiPS心臓（いのち）まで～」がテーマ\n「2025年大阪・関西万博」民間パビリオン\nCULTURE\n2023.06.23\n東利恵、隈研吾、妹島和世の3氏が日本女子大学の特別招聘教員に就任\n続報：開設予定の「建築デザイン学部（仮称）」&「建築デザイン研究科（仮称）」関連\nCULTURE\n2024.07.09\n\"こどものための建築\"が清春芸術村にオープン\n建築家の内田奈緒氏が設計、AI時代を生きる子どもたちへのメッセージが込められた〈遊びの塔ーtower of play〉\nCULTURE\n2024.10.30\n樹齢400年の倒木が支えるルーバー屋根の新たな杜\n隈研吾建築都市設計事務所が設計した、国宝建築の魅力"
  },
  "大阪・関西万博：Eataly Italian Pavilion Expo 2025 Osaka で素敵な ...": {
    "url": "https://eataly.co.jp/blogs/news/2025041002",
    "text": "大阪・関西万博：Eataly Italian Pavilion Expo 2025 Osaka で素敵な食体験をお楽しみください！\n – EATALY\nコンテンツに進む\nログイン/会員登録\n店舗情報\nイータリーについて\n店舗情報\nイータリー銀座店\nイータリー湘南店\nイータリー原宿店\nイータリー丸の内店\nイータリー日本橋店\n最新情報\nイベント\n新商品\n限定メニュー&商品\nクラス&セミナー\nインフォメーション\nイータリーについて\n問い合わせ\nイータリー・メンバーズ\n採用情報\n店舗情報\n戻る\nイータリー銀座店\nイータリー湘南店\nイータリー原宿店\nイータリー丸の内店\nイータリー日本橋店\n最新情報\n戻る\nイベント\n新商品\n限定メニュー&商品\nクラス&セミナー\nインフォメーション\nイータリーについて\n問い合わせ\nイータリー・メンバーズ\n採用情報\nカートにアイテムが追加されました\n買い物を続ける\nトップ\n最新情報\n大阪・関西万博：Eataly Italian Pavilion Expo 2025 Osaka で素敵な食体験をお楽しみください！\nイベント\n2025/04/10\n大阪・関西万博：Eataly Italian Pavilion Expo 2025 Osaka で素敵な食体験をお楽しみください！\nイタリア館で卓越したイタリア料理を\nイータリーはEXPO 2025大阪・関西万博に参加し、イタリア館内のレストランを運営しています。 イタリア館屋上の庭園を一望できるこのレストランでは、メイド・イン・イタリーの豊かな食材と多様性を称える\n唯一\n無二の食体験をお楽しみいただけます。\n食、文化、伝統を巡る本物の旅\n2025年4月13日から10月13日まで、イータリーのレストランは、イタリア料理の真髄を体験したい皆さんにとって格好のスポットとなります。 イタリアの\n18州の地域\nが週替わりで登場し、イタリアの並外れた生物多様性と、伝統のある食文化の物語を発見しながら、象徴的な料理や伝統的な名物料理を楽しむことができます。\nイータリーの哲学：味、品質、そして持続可能性\nユニークな郷土料理\n毎週異なるイタリアの州から各地方の伝統的な郷土料理が登場します。\n最高品質の食材\nすべての食材は、認証された持続可能な供給チェーンから調達され、土地と生産者を讃えています。\n美しい空間\nレストランにはテラス席がございます。店内外ともに居心地の良い雰囲気の中で、イタリア庭園を眺めながら、お食事をお楽しみいただけます。\nイタリア各地のカレンダー\n毎週、イタリア各地方の代表的な郷土料理がイータリーのレストランに登場します：\nヴェネツィアはプログラムの始まりを飾ります（4月13日〜19日）。\n・カラブリア州（4月20日〜26日）\n・フリウリ\n＝\nヴェネツィア・ジュリア州（4月27日〜5月3日）\n・ヴェネット\n州（5月4日〜10日）\n・\nプーリア州（\n5月11日〜17日）\n・ラツィオ州\n（5月18日〜24日）\n・マルケ州（\n6月1日〜7日）\n・シチリア州（6月8日〜14日）\n・アブルッツォ州（6月15日〜21日）\n・サルデーニャ州（6月22日〜28日）\n・リグーリア州（6月29日〜7月5日）\n・モリーゼ州（7月6日〜12日）\n・トスカーナ州\n（7月13日〜19日）\n・カンパニア州（7月20日〜30日 ※当初予定日から変更）\n・バジリカータ州（8月24日〜30日）\n・ウンブリア州（8月31日〜9月6日）\n・エミリア・ロマーニャ州（9月21日〜27日）\n・ピエモンテ州（9月28日〜10月4日）\n・ロンバルディア州（10月5日〜13日）\n営業時間：11:00 - 21:15（ラストオーダー20:20）\nイタリア館をご予約せずにレストランをご利用いただけます。\nレストランのご予約は賜っておりませんので、\nお\n時間に余裕を持ってご来店ください。\nレストランの\n入り口は、イタリアパビリオンの右側面奥にございます。直通エレベーターで3Fまでお上がりください。\nメニューはこちらからご参照ください。\nフードメニュー\nドリンクメニュー\n州のメニュー\n皆様ご来店お待ちしております。\n最新情報一覧に戻る\nイータリーは、EXPO 2025 大阪・関西万博\nイタリア館のダイアモンドスポンサーです。\nFollow Us\nイータリーについて\nコンセプト・歴史\n私たちのマニフェスト\nレストラン・カウンター\nマーケット\nイタリアン・ライフスタイル\n店舗情報\nイータリー銀座店\nイータリー湘南店\nイータリー原宿店\nイータリー丸の内店\nイータリー日本橋店\n最新情報\nイベント\n新商品\n限定メニュー&商品\nクラス&セミナー\nインフォメーション\nイータリー・マガジン\nストーリー\nレシピ\nカルチャー\nハウツー\nイータリー・メンバーズ\n会員プログラム\nLINEアカウント\nインフォメーション\nイータリーメンバーズ会員ガイド\nウェブサイト利用規約\nイータリーメンバーズ会員規約\nイータリーメンバーズ・ポイント利用規約\nプライバシーポリシー\n会社概要\n採用情報\n法人のお客様\nお問い合わせ\nCopyright © 2024 | Eataly SpA - All rights reserved JP\n選択結果を選ぶと、ページが全面的に更新されます。"
  }
}